LICENSE
MANIFEST.in
README.MD
setup.cfg
setup.py
version.py
meta_critique/__init__.py
meta_critique/cal_meta_scores.py
meta_critique/evaluate_aiu_precision.py
meta_critique/evaluate_aiu_recall.py
meta_critique/extracting_aius_for_critique.py
meta_critique/generate_ref_answer.py
meta_critique/generate_ref_critique.py
meta_critique/merge_files.py
meta_critique/meta_critique.py
meta_critique/openai_config.py
meta_critique/utils.py
meta_critique.egg-info/PKG-INFO
meta_critique.egg-info/SOURCES.txt
meta_critique.egg-info/dependency_links.txt
meta_critique.egg-info/requires.txt
meta_critique.egg-info/top_level.txt
meta_critique/prompts/.DS_Store
meta_critique/prompts/extract_aius.txt
meta_critique/prompts/precision.txt
meta_critique/prompts/recall.txt
meta_critique/prompts/reference_answer.txt
meta_critique/prompts/reference_critique.txt