Metadata-Version: 2.1
Name: meta-critique
Version: 0.1.2
Summary: Evaluate the Quality of Critique
Home-page: https://github.com/GAIR-NLP/MetaCritique
Author: GAIR Research Group
License: Apache License
Classifier: Intended Audience :: Developers
Classifier: Topic :: Text Processing
Classifier: Topic :: Scientific/Engineering :: Artificial Intelligence
Classifier: License :: OSI Approved :: Apache Software License
Classifier: Programming Language :: Python :: 3.9
Classifier: Programming Language :: Python :: 3.10
Classifier: Programming Language :: Python :: 3 :: Only
License-File: LICENSE
